Workbook
Name aporte: Simulador!$C$6
Name perfil: Simulador!$C$9
Name prazo_anos: Simulador!$C$7
Name salario: Simulador!$C$5
Name taxa_mensal: Simulador!$C$8

Sheet Simulador
B2: SIMULADOR DE INVESTIMENTOS EM FIIs
B5: Salário mensal | C5: 5000 | E5: Sugestão de aporte (30% do salário) | F5: =salario*30% -> 1500
B6: Aporte mensal | C6: 1000
B7: Prazo (anos) | C7: 10
B8: Rendimento mensal | C8: 0.008 | F8: DIVISÃO DO APORTE
B9: Perfil de investidor | C9: Moderado | F9: Tipo de fundo | G9: Percentual | H9: Aporte
F10: Tijolo | G10: =VLOOKUP($C$9&"_"&F10,Apoio!$A$2:$D$19,4,FALSE) -> 0.3 | H10: =$C$6*G10 -> 300
B11: RESULTADOS | F11: Papel | G11: =VLOOKUP($C$9&"_"&F11,Apoio!$A$2:$D$19,4,FALSE) -> 0.2 | H11: =$C$6*G11 -> 200
B12: Patrimônio acumulado | F12: Híbrido | G12: =VLOOKUP($C$9&"_"&F12,Apoio!$A$2:$D$19,4,FALSE) -> 0.2 | H12: =$C$6*G12 -> 200
B13: Dividendos mensais | C13: =C12*taxa_mensal -> 0 | F13: FOF | G13: =VLOOKUP($C$9&"_"&F13,Apoio!$A$2:$D$19,4,FALSE) -> 0.1 | H13: =$C$6*G13 -> 100
F14: Desenvolvimento | G14: =VLOOKUP($C$9&"_"&F14,Apoio!$A$2:$D$19,4,FALSE) -> 0.1 | H14: =$C$6*G14 -> 100
F15: Agro | G15: =VLOOKUP($C$9&"_"&F15,Apoio!$A$2:$D$19,4,FALSE) -> 0.1 | H15: =$C$6*G15 -> 100
B16: PROJEÇÃO POR PRAZO | F16: Total | G16: =SUM(G10:G15) -> 1 | H16: =SUM(H10:H15) -> 1000
B17: Prazo (anos) | C17: Patrimônio | D17: Dividendos/mês
B18: 2 | D18: =C18*taxa_mensal -> 0
B19: 5 | D19: =C19*taxa_mensal -> 0
B20: 10 | D20: =C20*taxa_mensal -> 0
B21: 20 | D21: =C21*taxa_mensal -> 0
B22: 30 | D22: =C22*taxa_mensal -> 0

Sheet Apoio
A1: Chave | B1: Perfil | C1: Tipo de fundo | D1: Percentual | F1: Perfil | G1: Total
A2: Conservador_Tijolo | B2: Conservador | C2: Tijolo | D2: 0.4 | F2: Conservador | G2: =SUMIF($B$2:$B$19,F2,$D$2:$D$19) -> 1
A3: Conservador_Papel | B3: Conservador | C3: Papel | D3: 0.3 | F3: Moderado | G3: =SUMIF($B$2:$B$19,F3,$D$2:$D$19) -> 1
A4: Conservador_Híbrido | B4: Conservador | C4: Híbrido | D4: 0.1 | F4: Arrojado | G4: =SUMIF($B$2:$B$19,F4,$D$2:$D$19) -> 1
A5: Conservador_FOF | B5: Conservador | C5: FOF | D5: 0.1
A6: Conservador_Desenvolvimento | B6: Conservador | C6: Desenvolvimento | D6: 0.05
A7: Conservador_Agro | B7: Conservador | C7: Agro | D7: 0.05
A8: Moderado_Tijolo | B8: Moderado | C8: Tijolo | D8: 0.3
A9: Moderado_Papel | B9: Moderado | C9: Papel | D9: 0.2
A10: Moderado_Híbrido | B10: Moderado | C10: Híbrido | D10: 0.2
A11: Moderado_FOF | B11: Moderado | C11: FOF | D11: 0.1
A12: Moderado_Desenvolvimento | B12: Moderado | C12: Desenvolvimento | D12: 0.1
A13: Moderado_Agro | B13: Moderado | C13: Agro | D13: 0.1
A14: Arrojado_Tijolo | B14: Arrojado | C14: Tijolo | D14: 0.15
A15: Arrojado_Papel | B15: Arrojado | C15: Papel | D15: 0.1
A16: Arrojado_Híbrido | B16: Arrojado | C16: Híbrido | D16: 0.2
... A19: Arrojado_Agro | B19: Arrojado | C19: Agro | D19: 0.2

Sheet README
A1: README — Simulador de Investimentos em FIIs
A3: Objetivo
A4: Simular patrimônio e dividendos a partir de aporte mensal, prazo e rendimento mensal.
A6: Perguntas respondidas
A7: 1. Quanto investir por mês? — Simulador!C6
A8: 2. Por quantos anos? — Simulador!C7
A9: 3. Qual a taxa de rendimento mensal? — Simulador!C8
A10: 4. Quanto de patrimônio acumular? — Simulador!C12 e tabela de cenários
A11: 5. Quanto receber de dividendos? — Simulador!C13
A13: Funções
A14: VF calcula o valor futuro dos aportes mensais. PROCV busca o percentual usando a chave Perfil_TipoDeFundo.
A16: Intervalos nomeados
... A23: Salário e aporte são valores de exemplo.
